yaucl/__init__.py
yaucl/base_config.py
yaucl/configholder.py
yaucl/env.py
yaucl/section_config.py
yaucl-0.2.0.dist-info/METADATA
yaucl-0.2.0.dist-info/WHEEL
yaucl-0.2.0.dist-info/licenses/LICENSE
yaucl-0.2.0.dist-info/RECORD
