Metadata-Version: 2.4
Name: yaucl
Version: 0.2.0
Summary: yet another user config library...
Project-URL: Homepage, https://github.com/djetelina/yaucl
Project-URL: Documentation, https://djetelina.github.io/yaucl
Project-URL: Repository, https://github.com/djetelina/yaucl
Project-URL: Changelog, https://github.com/djetelina/yaucl/blob/main/CHANGELOG.md
Author: David Jetelina
License-Expression: MIT
License-File: LICENSE
Keywords: conf,config,env,toml,user,userconfig,xdg
Requires-Python: >=3.10
Requires-Dist: platformdirs>=4.3.8
Requires-Dist: tomli>=2.2.1; python_full_version < '3.11'
Requires-Dist: typing-extensions>=4.13.2; python_full_version < '3.11'
